tibbers/__init__.py
tibbers/converter.py
tibbers/models/__init__.py
tibbers/models/pointnet.py
tibbers/models/cifar/__init__.py
tibbers/models/cifar/densenet.py
tibbers/models/cifar/efficientnet.py
tibbers/models/cifar/googlenet.py
tibbers/models/cifar/inceptionv4.py
tibbers/models/cifar/lenet.py
tibbers/models/cifar/mobilenet.py
tibbers/models/cifar/mobilenetv2.py
tibbers/models/cifar/nasnet.py
tibbers/models/cifar/resnet.py
tibbers/models/cifar/resnext.py
tibbers/models/cifar/senet.py
tibbers/models/cifar/shufflenet.py
tibbers/models/cifar/shufflenetv2.py
tibbers/models/cifar/vgg.py
tibbers/ops/__init__.py
tibbers/ops/batchnorm.py
tibbers/ops/conv.py
tibbers/ops/dropout2d.py
tibbers/ops/flatten.py
tibbers/ops/linear.py
tibbers/ops/multiheadattention.py
tibbers/ops/normalization.py
tibbers/ops/pooling.py
tibbers/ops/sparse.py
tibbers/ops/transformerencoderlayer.py
tibbers/ops/utils.py
tibbers/optim/__init__.py
tibbers/optim/_functional.py
tibbers/optim/adadelta.py
tibbers/optim/adam.py
tibbers/optim/lr_scheduler.py
tibbers/optim/partial.py
tibbers/optim/utils.py
tibbers-1.0.0.dev0.dist-info/METADATA
tibbers-1.0.0.dev0.dist-info/WHEEL
tibbers-1.0.0.dev0.dist-info/top_level.txt
tibbers-1.0.0.dev0.dist-info/RECORD
